{
  "version": "1.2.0",
  "chapters": [
    {
      "startTime": 0.0,
      "title": "Practice Meets Relationship",
      "url": "https://jeffharr.is/brensilver/talks/audiodharma-7186/?t=0"
    },
    {
      "startTime": 120.04,
      "title": "Relational Life as Mirror",
      "url": "https://jeffharr.is/brensilver/talks/audiodharma-7186/?t=120"
    },
    {
      "startTime": 448.44,
      "title": "Clinging and Belonging",
      "url": "https://jeffharr.is/brensilver/talks/audiodharma-7186/?t=448"
    },
    {
      "startTime": 704.48,
      "title": "Love’s Difficulty",
      "url": "https://jeffharr.is/brensilver/talks/audiodharma-7186/?t=704"
    },
    {
      "startTime": 937.36,
      "title": "Desire, Dependency, Risk",
      "url": "https://jeffharr.is/brensilver/talks/audiodharma-7186/?t=937"
    },
    {
      "startTime": 1494.168,
      "title": "Eros and Freedom",
      "url": "https://jeffharr.is/brensilver/talks/audiodharma-7186/?t=1494"
    },
    {
      "startTime": 2197.168,
      "title": "Aggression and Not-Self",
      "url": "https://jeffharr.is/brensilver/talks/audiodharma-7186/?t=2197"
    },
    {
      "startTime": 2907.068,
      "title": "Commitment and Refuge",
      "url": "https://jeffharr.is/brensilver/talks/audiodharma-7186/?t=2907"
    }
  ]
}
