{
  "version": "1.2.0",
  "chapters": [
    {
      "startTime": 0.0,
      "title": "Wholesome Pain",
      "url": "https://jeffharr.is/brensilver/talks/audiodharma-21700/?t=0"
    },
    {
      "startTime": 174.04,
      "title": "Suffering Efficiently",
      "url": "https://jeffharr.is/brensilver/talks/audiodharma-21700/?t=174"
    },
    {
      "startTime": 288.84,
      "title": "Love Without Control",
      "url": "https://jeffharr.is/brensilver/talks/audiodharma-21700/?t=289"
    },
    {
      "startTime": 423.48,
      "title": "Care And Grief",
      "url": "https://jeffharr.is/brensilver/talks/audiodharma-21700/?t=423"
    },
    {
      "startTime": 741.0,
      "title": "Compassion And Equanimity",
      "url": "https://jeffharr.is/brensilver/talks/audiodharma-21700/?t=741"
    },
    {
      "startTime": 1056.84,
      "title": "Vastness And Dukkha",
      "url": "https://jeffharr.is/brensilver/talks/audiodharma-21700/?t=1057"
    },
    {
      "startTime": 1516.568,
      "title": "Refining Compassion",
      "url": "https://jeffharr.is/brensilver/talks/audiodharma-21700/?t=1517"
    },
    {
      "startTime": 1762.288,
      "title": "Living With Change",
      "url": "https://jeffharr.is/brensilver/talks/audiodharma-21700/?t=1762"
    }
  ]
}
