{
  "version": "1.2.0",
  "chapters": [
    {
      "startTime": 0.0,
      "title": "Self-Love and Selflessness",
      "url": "https://jeffharr.is/brensilver/talks/dharmaseed-26520/?t=0"
    },
    {
      "startTime": 351.66,
      "title": "Worth and Success",
      "url": "https://jeffharr.is/brensilver/talks/dharmaseed-26520/?t=352"
    },
    {
      "startTime": 671.4,
      "title": "The Buddha on Not-Self",
      "url": "https://jeffharr.is/brensilver/talks/dharmaseed-26520/?t=671"
    },
    {
      "startTime": 1119.24,
      "title": "Grasping Makes the Self",
      "url": "https://jeffharr.is/brensilver/talks/dharmaseed-26520/?t=1119"
    },
    {
      "startTime": 1361.747,
      "title": "Seeing Through the Ground",
      "url": "https://jeffharr.is/brensilver/talks/dharmaseed-26520/?t=1362"
    },
    {
      "startTime": 1912.027,
      "title": "No Head, Gained World",
      "url": "https://jeffharr.is/brensilver/talks/dharmaseed-26520/?t=1912"
    },
    {
      "startTime": 2454.245,
      "title": "Face, Heart, and Compassion",
      "url": "https://jeffharr.is/brensilver/talks/dharmaseed-26520/?t=2454"
    },
    {
      "startTime": 2778.445,
      "title": "Practice Becomes Life",
      "url": "https://jeffharr.is/brensilver/talks/dharmaseed-26520/?t=2778"
    },
    {
      "startTime": 2897.885,
      "title": "Closing Meditation",
      "url": "https://jeffharr.is/brensilver/talks/dharmaseed-26520/?t=2898"
    }
  ]
}
