{
  "version": "1.2.0",
  "chapters": [
    {
      "startTime": 90.0,
      "title": "Opening the evening",
      "url": "https://jeffharr.is/brensilver/talks/dharmaseed-48356/?t=90"
    },
    {
      "startTime": 178.0,
      "title": "Reading the text together",
      "url": "https://jeffharr.is/brensilver/talks/dharmaseed-48356/?t=178"
    },
    {
      "startTime": 943.6,
      "title": "Metta as instruction",
      "url": "https://jeffharr.is/brensilver/talks/dharmaseed-48356/?t=944"
    },
    {
      "startTime": 1200.352,
      "title": "Pair work and daily use",
      "url": "https://jeffharr.is/brensilver/talks/dharmaseed-48356/?t=1200"
    },
    {
      "startTime": 1736.552,
      "title": "Repetition and reflection",
      "url": "https://jeffharr.is/brensilver/talks/dharmaseed-48356/?t=1737"
    },
    {
      "startTime": 3495.552,
      "title": "Suffering and consequence",
      "url": "https://jeffharr.is/brensilver/talks/dharmaseed-48356/?t=3496"
    },
    {
      "startTime": 4428.236,
      "title": "Benefits of metta",
      "url": "https://jeffharr.is/brensilver/talks/dharmaseed-48356/?t=4428"
    },
    {
      "startTime": 4787.836,
      "title": "Enemies and freedom",
      "url": "https://jeffharr.is/brensilver/talks/dharmaseed-48356/?t=4788"
    },
    {
      "startTime": 5013.751,
      "title": "Closing sit and walk",
      "url": "https://jeffharr.is/brensilver/talks/dharmaseed-48356/?t=5014"
    }
  ]
}
