{
  "version": "1.2.0",
  "chapters": [
    {
      "startTime": 0.0,
      "title": "Simple Attention",
      "url": "https://jeffharr.is/brensilver/talks/dharmaseed-41139/?t=0"
    },
    {
      "startTime": 346.96,
      "title": "Not Bracing",
      "url": "https://jeffharr.is/brensilver/talks/dharmaseed-41139/?t=347"
    },
    {
      "startTime": 541.68,
      "title": "From Breath to Feeling",
      "url": "https://jeffharr.is/brensilver/talks/dharmaseed-41139/?t=542"
    },
    {
      "startTime": 697.28,
      "title": "Body of Emotion",
      "url": "https://jeffharr.is/brensilver/talks/dharmaseed-41139/?t=697"
    },
    {
      "startTime": 974.4,
      "title": "Rolling Tides",
      "url": "https://jeffharr.is/brensilver/talks/dharmaseed-41139/?t=974"
    },
    {
      "startTime": 1416.971,
      "title": "Equanimity and Softening",
      "url": "https://jeffharr.is/brensilver/talks/dharmaseed-41139/?t=1417"
    },
    {
      "startTime": 1476.971,
      "title": "Listening to Thought",
      "url": "https://jeffharr.is/brensilver/talks/dharmaseed-41139/?t=1477"
    },
    {
      "startTime": 1823.971,
      "title": "Hearing the Narrator",
      "url": "https://jeffharr.is/brensilver/talks/dharmaseed-41139/?t=1824"
    },
    {
      "startTime": 1987.971,
      "title": "Feeling and Talk Together",
      "url": "https://jeffharr.is/brensilver/talks/dharmaseed-41139/?t=1988"
    }
  ]
}
