{
  "version": "1.2.0",
  "chapters": [
    {
      "startTime": 7.0,
      "title": "Opposites can both be true",
      "url": "https://jeffharr.is/brensilver/talks/dharmaseed-70766/?t=7"
    },
    {
      "startTime": 91.0,
      "title": "Acceptance without bargaining",
      "url": "https://jeffharr.is/brensilver/talks/dharmaseed-70766/?t=91"
    },
    {
      "startTime": 409.0,
      "title": "Growth points beyond self",
      "url": "https://jeffharr.is/brensilver/talks/dharmaseed-70766/?t=409"
    },
    {
      "startTime": 672.0,
      "title": "Seeing as love",
      "url": "https://jeffharr.is/brensilver/talks/dharmaseed-70766/?t=672"
    },
    {
      "startTime": 950.0,
      "title": "From states to traits",
      "url": "https://jeffharr.is/brensilver/talks/dharmaseed-70766/?t=950"
    },
    {
      "startTime": 1212.213,
      "title": "Home base of the heart",
      "url": "https://jeffharr.is/brensilver/talks/dharmaseed-70766/?t=1212"
    },
    {
      "startTime": 1445.133,
      "title": "Insight frees love",
      "url": "https://jeffharr.is/brensilver/talks/dharmaseed-70766/?t=1445"
    },
    {
      "startTime": 1751.773,
      "title": "Grief and non-clinging",
      "url": "https://jeffharr.is/brensilver/talks/dharmaseed-70766/?t=1752"
    },
    {
      "startTime": 2335.453,
      "title": "The cost of selfing",
      "url": "https://jeffharr.is/brensilver/talks/dharmaseed-70766/?t=2335"
    }
  ]
}
