{
  "version": "1.2.0",
  "chapters": [
    {
      "startTime": 9.0,
      "title": "Tranquility and clarity",
      "url": "https://jeffharr.is/dharma/brensilver/talks/audiodharma-20530/?t=9"
    },
    {
      "startTime": 116.0,
      "title": "Resting the body",
      "url": "https://jeffharr.is/dharma/brensilver/talks/audiodharma-20530/?t=116"
    },
    {
      "startTime": 318.0,
      "title": "Softening clinging",
      "url": "https://jeffharr.is/dharma/brensilver/talks/audiodharma-20530/?t=318"
    },
    {
      "startTime": 448.0,
      "title": "Body as a resource",
      "url": "https://jeffharr.is/dharma/brensilver/talks/audiodharma-20530/?t=448"
    },
    {
      "startTime": 654.0,
      "title": "Listening for silence",
      "url": "https://jeffharr.is/dharma/brensilver/talks/audiodharma-20530/?t=654"
    },
    {
      "startTime": 898.86,
      "title": "Silent listening",
      "url": "https://jeffharr.is/dharma/brensilver/talks/audiodharma-20530/?t=899"
    },
    {
      "startTime": 1057.32,
      "title": "Visual field and darkness",
      "url": "https://jeffharr.is/dharma/brensilver/talks/audiodharma-20530/?t=1057"
    },
    {
      "startTime": 1406.731,
      "title": "Letting clinging wait",
      "url": "https://jeffharr.is/dharma/brensilver/talks/audiodharma-20530/?t=1407"
    },
    {
      "startTime": 1549.731,
      "title": "Closing rest",
      "url": "https://jeffharr.is/dharma/brensilver/talks/audiodharma-20530/?t=1550"
    }
  ]
}
