{
  "version": "1.2.0",
  "chapters": [
    {
      "startTime": 12.0,
      "title": "Opening and Theme",
      "url": "https://jeffharr.is/dharma/brensilver/talks/audiodharma-19971/?t=12"
    },
    {
      "startTime": 57.0,
      "title": "Doubt as Disorientation",
      "url": "https://jeffharr.is/dharma/brensilver/talks/audiodharma-19971/?t=57"
    },
    {
      "startTime": 181.0,
      "title": "Narratives and Rumination",
      "url": "https://jeffharr.is/dharma/brensilver/talks/audiodharma-19971/?t=181"
    },
    {
      "startTime": 301.0,
      "title": "What Practice Cannot Do",
      "url": "https://jeffharr.is/dharma/brensilver/talks/audiodharma-19971/?t=301"
    },
    {
      "startTime": 458.0,
      "title": "Precision and Letting Go",
      "url": "https://jeffharr.is/dharma/brensilver/talks/audiodharma-19971/?t=458"
    },
    {
      "startTime": 604.0,
      "title": "Trusting Experience",
      "url": "https://jeffharr.is/dharma/brensilver/talks/audiodharma-19971/?t=604"
    },
    {
      "startTime": 659.0,
      "title": "Faith as a Hinge",
      "url": "https://jeffharr.is/dharma/brensilver/talks/audiodharma-19971/?t=659"
    },
    {
      "startTime": 735.0,
      "title": "Closing Encouragement",
      "url": "https://jeffharr.is/dharma/brensilver/talks/audiodharma-19971/?t=735"
    }
  ]
}
