{
  "version": "1.2.0",
  "chapters": [
    {
      "startTime": 0.0,
      "title": "Entering Gradually",
      "url": "https://jeffharr.is/dharma/brensilver/talks/audiodharma-24177/?t=0"
    },
    {
      "startTime": 114.88,
      "title": "Body Consent",
      "url": "https://jeffharr.is/dharma/brensilver/talks/audiodharma-24177/?t=115"
    },
    {
      "startTime": 256.36,
      "title": "Illusions of Control",
      "url": "https://jeffharr.is/dharma/brensilver/talks/audiodharma-24177/?t=256"
    },
    {
      "startTime": 376.36,
      "title": "Doing and Surrender",
      "url": "https://jeffharr.is/dharma/brensilver/talks/audiodharma-24177/?t=376"
    },
    {
      "startTime": 649.36,
      "title": "Balancing the Mind",
      "url": "https://jeffharr.is/dharma/brensilver/talks/audiodharma-24177/?t=649"
    },
    {
      "startTime": 793.36,
      "title": "Against Hierarchy",
      "url": "https://jeffharr.is/dharma/brensilver/talks/audiodharma-24177/?t=793"
    },
    {
      "startTime": 1045.36,
      "title": "Non-Distraction",
      "url": "https://jeffharr.is/dharma/brensilver/talks/audiodharma-24177/?t=1045"
    },
    {
      "startTime": 1163.36,
      "title": "Compassionate Balance",
      "url": "https://jeffharr.is/dharma/brensilver/talks/audiodharma-24177/?t=1163"
    }
  ]
}
