{
  "version": "1.2.0",
  "chapters": [
    {
      "startTime": 16.0,
      "title": "The Question of Practice",
      "url": "https://jeffharr.is/dharma/brensilver/talks/audiodharma-24176/?t=16"
    },
    {
      "startTime": 85.0,
      "title": "Letting the Question Dissolve",
      "url": "https://jeffharr.is/dharma/brensilver/talks/audiodharma-24176/?t=85"
    },
    {
      "startTime": 145.0,
      "title": "Answers and Letting Go",
      "url": "https://jeffharr.is/dharma/brensilver/talks/audiodharma-24176/?t=145"
    },
    {
      "startTime": 296.0,
      "title": "Sticky Thought",
      "url": "https://jeffharr.is/dharma/brensilver/talks/audiodharma-24176/?t=296"
    },
    {
      "startTime": 410.0,
      "title": "Attention, Not Answers",
      "url": "https://jeffharr.is/dharma/brensilver/talks/audiodharma-24176/?t=410"
    },
    {
      "startTime": 521.0,
      "title": "Relaxing the Need to Know",
      "url": "https://jeffharr.is/dharma/brensilver/talks/audiodharma-24176/?t=521"
    },
    {
      "startTime": 657.0,
      "title": "Dhammavichaya",
      "url": "https://jeffharr.is/dharma/brensilver/talks/audiodharma-24176/?t=657"
    },
    {
      "startTime": 807.0,
      "title": "Path and Goal",
      "url": "https://jeffharr.is/dharma/brensilver/talks/audiodharma-24176/?t=807"
    }
  ]
}
