{
  "version": "1.2.0",
  "chapters": [
    {
      "startTime": 0.0,
      "title": "Opening and settling",
      "url": "https://jeffharr.is/dharma/brensilver/talks/audiodharma-14008/?t=0"
    },
    {
      "startTime": 81.0,
      "title": "Remembering goodness",
      "url": "https://jeffharr.is/dharma/brensilver/talks/audiodharma-14008/?t=81"
    },
    {
      "startTime": 166.0,
      "title": "Lineage and gratitude",
      "url": "https://jeffharr.is/dharma/brensilver/talks/audiodharma-14008/?t=166"
    },
    {
      "startTime": 282.0,
      "title": "Resting in blessing",
      "url": "https://jeffharr.is/dharma/brensilver/talks/audiodharma-14008/?t=282"
    },
    {
      "startTime": 756.0,
      "title": "Sound as one field",
      "url": "https://jeffharr.is/dharma/brensilver/talks/audiodharma-14008/?t=756"
    },
    {
      "startTime": 827.0,
      "title": "Deepening into ease",
      "url": "https://jeffharr.is/dharma/brensilver/talks/audiodharma-14008/?t=827"
    },
    {
      "startTime": 1487.194,
      "title": "Letting the heart rest",
      "url": "https://jeffharr.is/dharma/brensilver/talks/audiodharma-14008/?t=1487"
    }
  ]
}
