{
  "version": "1.2.0",
  "chapters": [
    {
      "startTime": 0.0,
      "title": "Entering Silence",
      "url": "https://jeffharr.is/dharma/brensilver/talks/dharmaseed-93052/?t=0"
    },
    {
      "startTime": 84.0,
      "title": "Outer and Inner Sound",
      "url": "https://jeffharr.is/dharma/brensilver/talks/dharmaseed-93052/?t=84"
    },
    {
      "startTime": 208.0,
      "title": "No Preference",
      "url": "https://jeffharr.is/dharma/brensilver/talks/dharmaseed-93052/?t=208"
    },
    {
      "startTime": 451.0,
      "title": "Receptive Listening",
      "url": "https://jeffharr.is/dharma/brensilver/talks/dharmaseed-93052/?t=451"
    },
    {
      "startTime": 729.0,
      "title": "Body and Space",
      "url": "https://jeffharr.is/dharma/brensilver/talks/dharmaseed-93052/?t=729"
    },
    {
      "startTime": 910.0,
      "title": "Meaning and Fear",
      "url": "https://jeffharr.is/dharma/brensilver/talks/dharmaseed-93052/?t=910"
    },
    {
      "startTime": 1017.0,
      "title": "Dharma as Blessing",
      "url": "https://jeffharr.is/dharma/brensilver/talks/dharmaseed-93052/?t=1017"
    },
    {
      "startTime": 1172.0,
      "title": "Listening in Prayer",
      "url": "https://jeffharr.is/dharma/brensilver/talks/dharmaseed-93052/?t=1172"
    },
    {
      "startTime": 1624.321,
      "title": "Nonviolence in Practice",
      "url": "https://jeffharr.is/dharma/brensilver/talks/dharmaseed-93052/?t=1624"
    }
  ]
}
