{
  "version": "1.2.0",
  "chapters": [
    {
      "startTime": 0.0,
      "title": "Opening the inquiry",
      "url": "https://jeffharr.is/dharma/burbea/talks/dharmaseed-12525/?t=0"
    },
    {
      "startTime": 315.5,
      "title": "Working with difficulty",
      "url": "https://jeffharr.is/dharma/burbea/talks/dharmaseed-12525/?t=316"
    },
    {
      "startTime": 952.5,
      "title": "Metta as listening",
      "url": "https://jeffharr.is/dharma/burbea/talks/dharmaseed-12525/?t=952"
    },
    {
      "startTime": 1302.84,
      "title": "Intensity and spaciousness",
      "url": "https://jeffharr.is/dharma/burbea/talks/dharmaseed-12525/?t=1303"
    },
    {
      "startTime": 1723.2,
      "title": "From pain to compassion",
      "url": "https://jeffharr.is/dharma/burbea/talks/dharmaseed-12525/?t=1723"
    },
    {
      "startTime": 2300.44,
      "title": "Devotion to kindness",
      "url": "https://jeffharr.is/dharma/burbea/talks/dharmaseed-12525/?t=2300"
    },
    {
      "startTime": 2632.8,
      "title": "Metta and perception",
      "url": "https://jeffharr.is/dharma/burbea/talks/dharmaseed-12525/?t=2633"
    },
    {
      "startTime": 3725.0,
      "title": "Emptiness and jhana",
      "url": "https://jeffharr.is/dharma/burbea/talks/dharmaseed-12525/?t=3725"
    },
    {
      "startTime": 4156.0,
      "title": "Fabrication and dependent arising",
      "url": "https://jeffharr.is/dharma/burbea/talks/dharmaseed-12525/?t=4156"
    }
  ]
}
