{
  "version": "1.2.0",
  "chapters": [
    {
      "startTime": 1.0,
      "title": "Why This Delineation",
      "url": "https://jeffharr.is/dharma/burbea/talks/dharmaseed-40164/?t=1"
    },
    {
      "startTime": 140.0,
      "title": "Definitions and Context",
      "url": "https://jeffharr.is/dharma/burbea/talks/dharmaseed-40164/?t=140"
    },
    {
      "startTime": 346.0,
      "title": "Hermeneutic Circle",
      "url": "https://jeffharr.is/dharma/burbea/talks/dharmaseed-40164/?t=346"
    },
    {
      "startTime": 612.0,
      "title": "Eros as Desire",
      "url": "https://jeffharr.is/dharma/burbea/talks/dharmaseed-40164/?t=612"
    },
    {
      "startTime": 956.0,
      "title": "The More and Otherness",
      "url": "https://jeffharr.is/dharma/burbea/talks/dharmaseed-40164/?t=956"
    },
    {
      "startTime": 1449.92,
      "title": "Recognizing Eros",
      "url": "https://jeffharr.is/dharma/burbea/talks/dharmaseed-40164/?t=1450"
    },
    {
      "startTime": 1809.92,
      "title": "Juiciness and Arousal",
      "url": "https://jeffharr.is/dharma/burbea/talks/dharmaseed-40164/?t=1810"
    },
    {
      "startTime": 2222.92,
      "title": "Delight and Bliss",
      "url": "https://jeffharr.is/dharma/burbea/talks/dharmaseed-40164/?t=2223"
    }
  ]
}
