{
  "version": "1.2.0",
  "chapters": [
    {
      "startTime": 0.0,
      "title": "Music and limited hearing",
      "url": "https://jeffharr.is/dharma/burbea/talks/dharmaseed-40181/?t=0"
    },
    {
      "startTime": 74.0,
      "title": "Real or soul-making",
      "url": "https://jeffharr.is/dharma/burbea/talks/dharmaseed-40181/?t=74"
    },
    {
      "startTime": 497.0,
      "title": "Culture and realism",
      "url": "https://jeffharr.is/dharma/burbea/talks/dharmaseed-40181/?t=497"
    },
    {
      "startTime": 1095.0,
      "title": "Frameworks that support",
      "url": "https://jeffharr.is/dharma/burbea/talks/dharmaseed-40181/?t=1095"
    },
    {
      "startTime": 1561.973,
      "title": "Soulmaking and participation",
      "url": "https://jeffharr.is/dharma/burbea/talks/dharmaseed-40181/?t=1562"
    },
    {
      "startTime": 2087.493,
      "title": "Valid because valuable",
      "url": "https://jeffharr.is/dharma/burbea/talks/dharmaseed-40181/?t=2087"
    },
    {
      "startTime": 2800.943,
      "title": "Eros and development",
      "url": "https://jeffharr.is/dharma/burbea/talks/dharmaseed-40181/?t=2801"
    },
    {
      "startTime": 3566.943,
      "title": "Self, image, and pathology",
      "url": "https://jeffharr.is/dharma/burbea/talks/dharmaseed-40181/?t=3567"
    },
    {
      "startTime": 4232.804,
      "title": "Cracks in theory",
      "url": "https://jeffharr.is/dharma/burbea/talks/dharmaseed-40181/?t=4233"
    }
  ]
}
