{
  "version": "1.2.0",
  "chapters": [
    {
      "startTime": 0.0,
      "title": "Insight and metta",
      "url": "https://jeffharr.is/dharma/burbea/talks/dharmaseed-12291/?t=0"
    },
    {
      "startTime": 238.6,
      "title": "What insight means",
      "url": "https://jeffharr.is/dharma/burbea/talks/dharmaseed-12291/?t=239"
    },
    {
      "startTime": 390.52,
      "title": "Baba Amte's example",
      "url": "https://jeffharr.is/dharma/burbea/talks/dharmaseed-12291/?t=391"
    },
    {
      "startTime": 647.36,
      "title": "Working with fear",
      "url": "https://jeffharr.is/dharma/burbea/talks/dharmaseed-12291/?t=647"
    },
    {
      "startTime": 1493.0,
      "title": "Insight in practice",
      "url": "https://jeffharr.is/dharma/burbea/talks/dharmaseed-12291/?t=1493"
    },
    {
      "startTime": 1615.0,
      "title": "Three characteristics",
      "url": "https://jeffharr.is/dharma/burbea/talks/dharmaseed-12291/?t=1615"
    },
    {
      "startTime": 2177.0,
      "title": "Not-self and openness",
      "url": "https://jeffharr.is/dharma/burbea/talks/dharmaseed-12291/?t=2177"
    },
    {
      "startTime": 2925.0,
      "title": "Unhooking me and mine",
      "url": "https://jeffharr.is/dharma/burbea/talks/dharmaseed-12291/?t=2925"
    },
    {
      "startTime": 3462.0,
      "title": "Habits, grooves, and trust",
      "url": "https://jeffharr.is/dharma/burbea/talks/dharmaseed-12291/?t=3462"
    }
  ]
}
