{
  "version": "1.2.0",
  "chapters": [
    {
      "startTime": 30.0,
      "title": "Framing the Tipping Point",
      "url": "https://jeffharr.is/dharma/burbea/talks/dharmaseed-16516/?t=30"
    },
    {
      "startTime": 206.4,
      "title": "Callenbach’s Final Vision",
      "url": "https://jeffharr.is/dharma/burbea/talks/dharmaseed-16516/?t=206"
    },
    {
      "startTime": 495.04,
      "title": "Hope and Mutual Support",
      "url": "https://jeffharr.is/dharma/burbea/talks/dharmaseed-16516/?t=495"
    },
    {
      "startTime": 809.6,
      "title": "Hard Times, Regeneration",
      "url": "https://jeffharr.is/dharma/burbea/talks/dharmaseed-16516/?t=810"
    },
    {
      "startTime": 1461.931,
      "title": "From Me to We",
      "url": "https://jeffharr.is/dharma/burbea/talks/dharmaseed-16516/?t=1462"
    },
    {
      "startTime": 1816.491,
      "title": "Five Commitments",
      "url": "https://jeffharr.is/dharma/burbea/talks/dharmaseed-16516/?t=1816"
    },
    {
      "startTime": 2426.284,
      "title": "Interbeing in the Body",
      "url": "https://jeffharr.is/dharma/burbea/talks/dharmaseed-16516/?t=2426"
    }
  ]
}
