{
  "version": "1.2.0",
  "chapters": [
    {
      "startTime": 1.0,
      "title": "A Map of Practice",
      "url": "https://jeffharr.is/dharma/burbea/talks/dharmaseed-11120/?t=1"
    },
    {
      "startTime": 145.0,
      "title": "Time Feels Solid",
      "url": "https://jeffharr.is/dharma/burbea/talks/dharmaseed-11120/?t=145"
    },
    {
      "startTime": 337.0,
      "title": "Past and Future",
      "url": "https://jeffharr.is/dharma/burbea/talks/dharmaseed-11120/?t=337"
    },
    {
      "startTime": 605.0,
      "title": "Awareness and Time",
      "url": "https://jeffharr.is/dharma/burbea/talks/dharmaseed-11120/?t=605"
    },
    {
      "startTime": 806.0,
      "title": "One or Many",
      "url": "https://jeffharr.is/dharma/burbea/talks/dharmaseed-11120/?t=806"
    },
    {
      "startTime": 1129.0,
      "title": "Arising From None",
      "url": "https://jeffharr.is/dharma/burbea/talks/dharmaseed-11120/?t=1129"
    },
    {
      "startTime": 1396.41,
      "title": "The Tripod of Self",
      "url": "https://jeffharr.is/dharma/burbea/talks/dharmaseed-11120/?t=1396"
    },
    {
      "startTime": 2160.17,
      "title": "Dependent Arising Deepens",
      "url": "https://jeffharr.is/dharma/burbea/talks/dharmaseed-11120/?t=2160"
    },
    {
      "startTime": 2661.542,
      "title": "Subtle Mind Factors",
      "url": "https://jeffharr.is/dharma/burbea/talks/dharmaseed-11120/?t=2662"
    }
  ]
}
