{
  "version": "1.2.0",
  "chapters": [
    {
      "startTime": 0.0,
      "title": "Opening Questions",
      "url": "https://jeffharr.is/dharma/burbea/talks/dharmaseed-43949/?t=0"
    },
    {
      "startTime": 442.2,
      "title": "Culture and Self",
      "url": "https://jeffharr.is/dharma/burbea/talks/dharmaseed-43949/?t=442"
    },
    {
      "startTime": 752.12,
      "title": "Soulmaking Test",
      "url": "https://jeffharr.is/dharma/burbea/talks/dharmaseed-43949/?t=752"
    },
    {
      "startTime": 1201.797,
      "title": "Eros and Beyond",
      "url": "https://jeffharr.is/dharma/burbea/talks/dharmaseed-43949/?t=1202"
    },
    {
      "startTime": 1765.977,
      "title": "Horizontal Craving",
      "url": "https://jeffharr.is/dharma/burbea/talks/dharmaseed-43949/?t=1766"
    },
    {
      "startTime": 2530.922,
      "title": "Four Path Imaginations",
      "url": "https://jeffharr.is/dharma/burbea/talks/dharmaseed-43949/?t=2531"
    },
    {
      "startTime": 3366.142,
      "title": "Tantra and Imaginal",
      "url": "https://jeffharr.is/dharma/burbea/talks/dharmaseed-43949/?t=3366"
    },
    {
      "startTime": 3880.421,
      "title": "Open-Ended Awakening",
      "url": "https://jeffharr.is/dharma/burbea/talks/dharmaseed-43949/?t=3880"
    },
    {
      "startTime": 5036.496,
      "title": "Questions to Carry",
      "url": "https://jeffharr.is/dharma/burbea/talks/dharmaseed-43949/?t=5036"
    }
  ]
}
