{
  "version": "1.2.0",
  "chapters": [
    {
      "startTime": 351.02,
      "title": "Opening the Topic",
      "url": "https://jeffharr.is/dharma/burbea/talks/dharmaseed-60888/?t=351"
    },
    {
      "startTime": 392.02,
      "title": "Canonical Description",
      "url": "https://jeffharr.is/dharma/burbea/talks/dharmaseed-60888/?t=392"
    },
    {
      "startTime": 459.02,
      "title": "Awareness Knows Itself",
      "url": "https://jeffharr.is/dharma/burbea/talks/dharmaseed-60888/?t=459"
    },
    {
      "startTime": 667.02,
      "title": "How Attention Settles",
      "url": "https://jeffharr.is/dharma/burbea/talks/dharmaseed-60888/?t=667"
    },
    {
      "startTime": 1066.02,
      "title": "Intensity and Release",
      "url": "https://jeffharr.is/dharma/burbea/talks/dharmaseed-60888/?t=1066"
    },
    {
      "startTime": 1214.606,
      "title": "Vastness Compared",
      "url": "https://jeffharr.is/dharma/burbea/talks/dharmaseed-60888/?t=1215"
    },
    {
      "startTime": 1612.446,
      "title": "After-Effects and Truth",
      "url": "https://jeffharr.is/dharma/burbea/talks/dharmaseed-60888/?t=1612"
    },
    {
      "startTime": 2500.076,
      "title": "Paths In and View",
      "url": "https://jeffharr.is/dharma/burbea/talks/dharmaseed-60888/?t=2500"
    },
    {
      "startTime": 3541.856,
      "title": "Training, Desire, and Use",
      "url": "https://jeffharr.is/dharma/burbea/talks/dharmaseed-60888/?t=3542"
    }
  ]
}
