{
  "version": "1.2.0",
  "chapters": [
    {
      "startTime": 0.0,
      "title": "Ethics and dimensionality",
      "url": "https://jeffharr.is/dharma/burbea/talks/dharmaseed-61075/?t=0"
    },
    {
      "startTime": 558.44,
      "title": "Voluntarism and scripture",
      "url": "https://jeffharr.is/dharma/burbea/talks/dharmaseed-61075/?t=558"
    },
    {
      "startTime": 865.8,
      "title": "Reformation and modern flattening",
      "url": "https://jeffharr.is/dharma/burbea/talks/dharmaseed-61075/?t=866"
    },
    {
      "startTime": 1717.201,
      "title": "Augustine and ordered love",
      "url": "https://jeffharr.is/dharma/burbea/talks/dharmaseed-61075/?t=1717"
    },
    {
      "startTime": 2396.161,
      "title": "Modern cosmos, participatory reality",
      "url": "https://jeffharr.is/dharma/burbea/talks/dharmaseed-61075/?t=2396"
    },
    {
      "startTime": 3342.466,
      "title": "Soulmaking and the world",
      "url": "https://jeffharr.is/dharma/burbea/talks/dharmaseed-61075/?t=3342"
    },
    {
      "startTime": 5218.894,
      "title": "Rationality and the Logos",
      "url": "https://jeffharr.is/dharma/burbea/talks/dharmaseed-61075/?t=5219"
    },
    {
      "startTime": 6668.5,
      "title": "Limits of rational ethics",
      "url": "https://jeffharr.is/dharma/burbea/talks/dharmaseed-61075/?t=6668"
    },
    {
      "startTime": 8055.913,
      "title": "What lies behind reduction",
      "url": "https://jeffharr.is/dharma/burbea/talks/dharmaseed-61075/?t=8056"
    }
  ]
}
