{
  "version": "1.2.0",
  "chapters": [
    {
      "startTime": 0.0,
      "title": "Eros Opens Meaning",
      "url": "https://jeffharr.is/dharma/burbea/talks/dharmaseed-40174/?t=0"
    },
    {
      "startTime": 152.24,
      "title": "Infinite Interpretation",
      "url": "https://jeffharr.is/dharma/burbea/talks/dharmaseed-40174/?t=152"
    },
    {
      "startTime": 424.16,
      "title": "Buddha Nature Language",
      "url": "https://jeffharr.is/dharma/burbea/talks/dharmaseed-40174/?t=424"
    },
    {
      "startTime": 577.72,
      "title": "When Eros Narrows",
      "url": "https://jeffharr.is/dharma/burbea/talks/dharmaseed-40174/?t=578"
    },
    {
      "startTime": 748.88,
      "title": "Dream of the Door",
      "url": "https://jeffharr.is/dharma/burbea/talks/dharmaseed-40174/?t=749"
    },
    {
      "startTime": 1036.92,
      "title": "Relationships And Limits",
      "url": "https://jeffharr.is/dharma/burbea/talks/dharmaseed-40174/?t=1037"
    },
    {
      "startTime": 1449.663,
      "title": "Icon, Idol, Concept",
      "url": "https://jeffharr.is/dharma/burbea/talks/dharmaseed-40174/?t=1450"
    },
    {
      "startTime": 1753.663,
      "title": "Temenos And Containment",
      "url": "https://jeffharr.is/dharma/burbea/talks/dharmaseed-40174/?t=1754"
    },
    {
      "startTime": 2135.663,
      "title": "James On Desire",
      "url": "https://jeffharr.is/dharma/burbea/talks/dharmaseed-40174/?t=2136"
    }
  ]
}
