{
  "version": "1.2.0",
  "chapters": [
    {
      "startTime": 1.0,
      "title": "Inquiry as intimacy",
      "url": "https://jeffharr.is/dharma/burbea/talks/dharmaseed-13847/?t=1"
    },
    {
      "startTime": 223.0,
      "title": "Questions that open",
      "url": "https://jeffharr.is/dharma/burbea/talks/dharmaseed-13847/?t=223"
    },
    {
      "startTime": 485.0,
      "title": "Experiment and possibility",
      "url": "https://jeffharr.is/dharma/burbea/talks/dharmaseed-13847/?t=485"
    },
    {
      "startTime": 1021.0,
      "title": "What blocks questioning",
      "url": "https://jeffharr.is/dharma/burbea/talks/dharmaseed-13847/?t=1021"
    },
    {
      "startTime": 1493.211,
      "title": "Ideas shape experience",
      "url": "https://jeffharr.is/dharma/burbea/talks/dharmaseed-13847/?t=1493"
    },
    {
      "startTime": 1968.091,
      "title": "Passion for truth",
      "url": "https://jeffharr.is/dharma/burbea/talks/dharmaseed-13847/?t=1968"
    },
    {
      "startTime": 2465.152,
      "title": "Comfort, certainty, and dissonance",
      "url": "https://jeffharr.is/dharma/burbea/talks/dharmaseed-13847/?t=2465"
    },
    {
      "startTime": 3328.152,
      "title": "Frameworks and observation",
      "url": "https://jeffharr.is/dharma/burbea/talks/dharmaseed-13847/?t=3328"
    },
    {
      "startTime": 3773.312,
      "title": "Cracking open the vessel",
      "url": "https://jeffharr.is/dharma/burbea/talks/dharmaseed-13847/?t=3773"
    }
  ]
}
