{
  "version": "1.2.0",
  "chapters": [
    {
      "startTime": 0.0,
      "title": "Fragile Earth",
      "url": "https://jeffharr.is/dharma/burbea/talks/dharmaseed-22994/?t=0"
    },
    {
      "startTime": 121.44,
      "title": "Seeing the Iceberg",
      "url": "https://jeffharr.is/dharma/burbea/talks/dharmaseed-22994/?t=121"
    },
    {
      "startTime": 530.2,
      "title": "Reading Extinction",
      "url": "https://jeffharr.is/dharma/burbea/talks/dharmaseed-22994/?t=530"
    },
    {
      "startTime": 680.28,
      "title": "Beyond Climate Alone",
      "url": "https://jeffharr.is/dharma/burbea/talks/dharmaseed-22994/?t=680"
    },
    {
      "startTime": 1208.102,
      "title": "What Awakening Means",
      "url": "https://jeffharr.is/dharma/burbea/talks/dharmaseed-22994/?t=1208"
    },
    {
      "startTime": 2026.342,
      "title": "Growth and Alienation",
      "url": "https://jeffharr.is/dharma/burbea/talks/dharmaseed-22994/?t=2026"
    },
    {
      "startTime": 2589.839,
      "title": "Intimacy With the World",
      "url": "https://jeffharr.is/dharma/burbea/talks/dharmaseed-22994/?t=2590"
    },
    {
      "startTime": 2984.839,
      "title": "A Spiritual Crisis",
      "url": "https://jeffharr.is/dharma/burbea/talks/dharmaseed-22994/?t=2985"
    }
  ]
}
