{
  "version": "1.2.0",
  "chapters": [
    {
      "startTime": 0.0,
      "title": "Opening chant",
      "url": "https://jeffharr.is/dharma/burbea/talks/dharmaseed-20660/?t=0"
    },
    {
      "startTime": 1209.613,
      "title": "Facing unavoidable change",
      "url": "https://jeffharr.is/dharma/burbea/talks/dharmaseed-20660/?t=1210"
    },
    {
      "startTime": 1296.613,
      "title": "Butterfly transformation",
      "url": "https://jeffharr.is/dharma/burbea/talks/dharmaseed-20660/?t=1297"
    },
    {
      "startTime": 1486.613,
      "title": "Seeing without forcing",
      "url": "https://jeffharr.is/dharma/burbea/talks/dharmaseed-20660/?t=1487"
    },
    {
      "startTime": 1566.613,
      "title": "Mara becomes flowers",
      "url": "https://jeffharr.is/dharma/burbea/talks/dharmaseed-20660/?t=1567"
    },
    {
      "startTime": 1647.613,
      "title": "Inner and outer climate",
      "url": "https://jeffharr.is/dharma/burbea/talks/dharmaseed-20660/?t=1648"
    },
    {
      "startTime": 1860.613,
      "title": "Paññā and insight",
      "url": "https://jeffharr.is/dharma/burbea/talks/dharmaseed-20660/?t=1861"
    },
    {
      "startTime": 2000.613,
      "title": "Where practice interrupts",
      "url": "https://jeffharr.is/dharma/burbea/talks/dharmaseed-20660/?t=2001"
    }
  ]
}
