{
  "version": "1.2.0",
  "chapters": [
    {
      "startTime": 0.0,
      "title": "Returning to Vedanta",
      "url": "https://jeffharr.is/dharma/watts/talks/watts-bb0528-10/?t=0"
    },
    {
      "startTime": 54.14,
      "title": "God, self, and masks",
      "url": "https://jeffharr.is/dharma/watts/talks/watts-bb0528-10/?t=54"
    },
    {
      "startTime": 226.74,
      "title": "Liberation from convention",
      "url": "https://jeffharr.is/dharma/watts/talks/watts-bb0528-10/?t=227"
    },
    {
      "startTime": 349.4,
      "title": "The limits of social identity",
      "url": "https://jeffharr.is/dharma/watts/talks/watts-bb0528-10/?t=349"
    },
    {
      "startTime": 641.16,
      "title": "Maya reconsidered",
      "url": "https://jeffharr.is/dharma/watts/talks/watts-bb0528-10/?t=641"
    },
    {
      "startTime": 865.92,
      "title": "The Gita on action",
      "url": "https://jeffharr.is/dharma/watts/talks/watts-bb0528-10/?t=866"
    },
    {
      "startTime": 1038.26,
      "title": "Into the world again",
      "url": "https://jeffharr.is/dharma/watts/talks/watts-bb0528-10/?t=1038"
    },
    {
      "startTime": 1321.624,
      "title": "Affirmation, not escape",
      "url": "https://jeffharr.is/dharma/watts/talks/watts-bb0528-10/?t=1322"
    }
  ]
}
